tugaphone/__init__.py
tugaphone/espeak.py
tugaphone/regional_dict.csv
tugaphone/util.py
tugaphone/version.py
tugaphone-0.0.2.dist-info/METADATA
tugaphone-0.0.2.dist-info/WHEEL
tugaphone-0.0.2.dist-info/top_level.txt
tugaphone-0.0.2.dist-info/RECORD
