Metadata-Version: 2.1
Name: tugaphone
Version: 0.0.2
Home-page: https://github.com/TigreGotico/tugaphone
Author: JarbasAi
Author-email: jarbasai@mailfence.com
Requires-Dist: spacy
